condorcet/__init__.py
condorcet/evaluator.py
condorcet/utils.py
LICENSE
condorcet-0.1.1.dist-info/LICENSE
condorcet-0.1.1.dist-info/WHEEL
condorcet-0.1.1.dist-info/METADATA
condorcet-0.1.1.dist-info/RECORD
