Metadata-Version: 2.1
Name: condorcet
Version: 0.1.1
Summary: Condorcet is a utility for evaluating votes using the condorcet method
Home-page: https://gitlab.com/a-thousand-juniors/condorcet
License: MIT
Keywords: condorcet,condorcet method,pairwise vote count,preferential voting
Author: Mfon Eti-mfon
Author-email: mfonetimfon@gmail.com
Requires-Python: >=3.8,<4.0
Classifier: License :: OSI Approved :: MIT License
Classifier: Operating System :: OS Independent
Classifier: Programming Language :: Python
Classifier: Programming Language :: Python :: 3
Classifier: Programming Language :: Python :: 3.8
Classifier: Programming Language :: Python :: 3.9
Requires-Dist: pytest-mock (>=3.6.1,<4.0.0)
Project-URL: Repository, https://gitlab.com/a-thousand-juniors/condorcet
